{
  "id": "case-2005고합1157",
  "category": "형사",
  "sub_category": "사기",
  "type": "case",
  "title": "대법원 2005고합1157 판결",
  "content": "【사건 개요】\n피고인: 피고인 1\n외 3인\n\n【판단】\n위 각 공소사실에 대하여 검사는 한국마사회법 제50조 제1호 , 제48조 제2항 으로 공소를 제기하였는데, 동 법 제48조(유사행위의 금지 등) 제2항 은 “마사회가 아닌 자는 마사회가 시행하는 경주에 관하여 승마투표와\n유사한 행위를 하게 하여 적중자에게 재물 또는 재산상의 이익을 교부하는 행위를 할 수 없다.”고 규정하고\n있다 위와 같은 동법 제48조 제2항 의 법문언, 동법 제59조 제2호 에서 ‘ 제48조 제2항 의 규정에 의한 행위의 상 대가 된 자’에 대해서도 1년 이하의 징역 또는 300만 원 이하의 벌금에 처하도록 규정하고 있는 점을 체계적\n으로 해석해보면, 동법 제48조 제2항 에서 금지하고 있는 유사행위는 경마참가자들이 ‘마사회가 아닌 자가 소 위 사설경마를 한다는 사정’을 알면서도 그 자에게 ‘마사회에 대하여 하는 승마투표와 유사하게’ 투표를 할 것\n을 요건으로 한다고 할 것이다 이 사건에 관하여 보건대, 앞서 특정경제범죄 가중처벌 등에 관한 법률 위반(사기)죄, 상습사기죄에 대한 부분\n에서 판단한 것과 같이, 피고인들은 경마경주권의 구매를 대행해주겠다고 피해자들을 기망하였고 이에 속은\n서울중앙지법 2006.4.21. 선고 2005고합1157 판결 : 항소\n5피해자들은 자신들이 ‘마사회에 대하여 승마투표를 한다고 생각하면서’ 투표를 한 것이므로, 피해자들이 ‘마사\n회가 아닌 자에게 승마투표와 유사한 행위’를 하였다고 할 수 없고, 설사 피고인들이 피해자들 중 적중한 자 에게 당첨금을 지급하였다고 할지라도 이는 자신들이 피해자들을 기망하였다는 사정을 감추고 계속적으로 피 해자들로부터 경주권 구매대행 명목으로 돈을 교부받아 편취하기 위한 방편에 불과하다고 할 것이므로, 피고\n인들의 이러한 행위가 사기죄에 해당함은 별론으로 하되 한국마사회법 제48조 제2항 이 금지하고 있는 유사\n행위에는 해당하지 아니한다고 할 것이다 달리, 피고인들이 ‘퀸레이스’, ‘세이레이스’ 사이트를 운영하면서 이용자들에게 자신들이 소위 사설경마를 운영\n하는 것이라는 점을 알렸고, 이용자들도 자신들이 피고인들이 운영하는 사설경마의 상대자가 된다는 사정을\n알면서도 피고인들에게 승마투표와 유사한 행위를 하였으며, 그에 따라 피고인들이 이용자들 중 적중자에게\n당첨금을 지급하였음을 인정할 증거가 없으므로, 위 각 공소사실은 범죄의 증명이 없는 때에 해당하여 형사소\n송법 제325조 후단에 의하여 피고인들에 대하여 각 무죄를 선고한다. {반면, 경륜·경정법의 경우 제21조 (유사행위의 금지)가 “경주사업자가 아닌 자는 승자투표권 또는 이와 유사\n한 것을 발매하거나 승자투표적중자에 대하여 금전을 교부하는 경주 및 승자투표권의 구매·알선·양도 등과 관 련한 일체의 영리행위를 하여서는 아니 된다.”고 규정하고 있어, ‘승자투표권 등 발매행위’, ‘승자투표자에 대 한 금전 교부 행위’, ‘승자투표권의 구매·알선·양도 등’ 중 어느 하나만 위반하여도 위 규정을 위반한 것이 될 뿐만 아니라( 대법원 2005. 4. 15. 선고 2004도8971 판결 참조), 한국마사회법과 같이 사설경주행위의 상대\n자를 처벌하는 규정도 없으므로, 피고인들이 위 각 사이트를 운영하면서 경륜·경정 경주권을 구매대행해주겠\n다고 피해자들을 기망하였고 이에 속은 피해자들이 ‘경륜본부 또는 경정본부에 대하여 승자투표를 한다고 생 각하면서’ 경주권 구입비 명목의 돈을 교부함으로써 피해자들에 대한 사기죄가 성립함은 물론이고, 나아가 피 고인들이 피해자들 중 적중한 자에게 당첨금을 지급함으로써 경륜·경정법 제24조 제1항 제1호 , 제21조 에 해당하여 별도로 경륜·경정법 위반죄도 성립한다.}\n피고인들의 주장에 대한 판단\n피고인들은, 자신들이 운영한 ‘퀸레이스’, ‘세이레이스’ 인터넷사이트에 ‘구매대행’이라는 용어는 사용하지 않은\n점, 구매대행 수수료를 받지 아니하고 입금액의 20%를 이벤트머니로서 추가적으로 지급한 점, 1회 투표금액\n을 한국마사회 및 경륜·경정본부보다 높은 20만 원으로 정했고, 당첨금을 1천만 원으로 제한하였던 점, 경주\n무효 등과 같은 극히 예외적인 사정이 있는 경우에만 투표권구입을 취소하여 주며 원칙적으로 투표권구입의\n취소를 허용하지 않는 한국마사회 및 경륜·경정본부와 달리, 피고인들은 투표마감시각 3분 전까지 투표권구입\n의 취소를 전면적으로 인정하였고, 또 투표마감시각까지 투표권의 구입을 가능토록 한 점, 피고인들은 투표적\n중자에게 당첨금을 모두 지급한 점을 들면서, 자신들은 위 인터넷사이트를 운영함에 있어 이용자들을 기망한\n바 없고, 이용자들로서도 위 인터넷사이트에서 경주권을 실제로 구매하지는 않는다는 점을 충분히 알면서도\n단지 투표적중시 당첨금을 받고자 하는 의도로 피고인들에게 돈을 송금한 것이므로, 이용자들이 피고인들로부\n터 돈을 편취당했다고는 할 수 없다고 주장한다 그러나 ① 피고인들은 ‘퀸레이스’, ‘세이레이스’ 인터넷사이트를 운영하면서 ‘구매대행’이라는 표현은 사용하지\n않았으나, ‘경주권 구매’, ‘실시간 배당’, ‘당첨금 지급’이라는 표현을 사용하였고, 한국마사회, 경륜·경정본부가\n운영하는 각 경주의 일정, 출주표, 배당률, 결과 등을 실시간으로 구체적으로 게재하였으며, 그 밖에 위 사이\n트들의 화면구성, 내용들을 종합해 보면, 정보통신기술이 고도로 발달한 현대사회를 사는 이용자들로서는 ‘자 신들이 피고인들에게 경주권 구매를 의뢰하면, 피고인들이 실제 경마장·경륜장·경정장의 창구에 나가 경주권을\n구입하는 것’이 아니라, 위 사이트들이 한국마사회 및 경륜·경정본부가 직접 운영하는 것이던지 혹은 그 기관\n들로부터 허가를 받거나 운영을 위임받아 대행운영을 하는 것으로서 위 기관들이 운영하는 컴퓨터서버와 연결\n되어 전산상 실시간으로 경주권 구매가 이루어진다고 오인하기 쉽도록 되어 있으며, ② 이용자들의 주된 관심\n은 자신들의 투표 당첨 여부와 당첨금 지급 여부에 있었겠지만, 위 사이트들이 위 기관들과 아무런 관련이 없 는 무허가 사설업체라든가 이른바 사설경마를 하는 업체라는 것을 알았다면, 당첨금이 지급되지 않을 위험이\n현저히 높은 피고인들에게 경주권 구매를 의뢰하지 않았을 것이 분명하고, ③ 피고인들은 애당초 이용자들이\n의뢰한 대로 경주권을 구매할 의사가 전혀 없었음에도, 자신들이 사설업체로서 경주를 운영한다는 점을 이용\n자들에게 고지하지 아니하고 마치 위 기관들이 직접 운영하거나 위 기관들로부터 위임을 받아 운영을 하는 것 서울중앙지법 2006.4.21. 선고 2005고합1157 판결 : 항소\n6처럼 인터넷사이트를 만들어 운영하면서 경주권 구입비 명목으로 돈을 송금받은 이상, 피고인들은 이용자들을\n기망하여 돈을 편취한 것이라고 할 것이고, ④ 피고인들이 구매를 의뢰받은 경주권 중 당첨된 경주권에 대하\n여 그 구매를 의뢰하였던 이용자에게 당첨금을 전부 지급하였다고 하더라도, 이용자들은 피고인들이 한국마사\n회, 경륜·경정본부를 대행하거나 위 기관으로부터 당첨금을 수령하여 이용자들에게 전달하여 주는 것으로 알 고 있었던 것으로서, 이는 인터넷사이트의 계속적인 영업을 위하여 고객이탈방지 차원에서 한 행위에 불과하\n므로, 피고인들에게 편취의 범의가 없었다고 할 수 없다 따라서 피고인들의 주장은 이유 없다 피고인 1 은 집행유예 기간 중에 있음에도 불구하고, 경주권 구매대행업을 가장하여 이 사건 각 인터넷사이트\n를 운영하여 편취한 돈이 약 15억 원에 이르므로, 그 죄질과 범정이 중하나, 위 돈 중 상당 부분이 당첨금으\n로 지급된 것으로 보이는 점, 피고인에게 동종전과가 없는 점, 피고인이 자신의 잘못을 뉘우치고 있는 점, 기 타 피고인의 연령, 성행, 환경 등 이 사건에 나타난 제반 양형조건들을 참작하여, 작량감경한 형기 범위 내에\n서 주문과 같이 형을 정한다 피고인 2 는 피고인 1 로부터 봉급 이외에 영업이익의 20%를 추가로 배분받기로 약속받았고, 상급자로서 다 른 직원들을 관리하는 위치에 있었던 점, 실제로 피고인 1 로부터 배분받은 돈은 그리 많지 않고 초범인 점,\n피고인이 자신의 잘못을 깊이 뉘우치고 있는 점, 기타 피고인의 연령, 성행, 환경 등 이 사건에 나타난 제반\n양형조건들을 참작하여 작량감경한 형기 범위 내에서 주문과 같이 형을 정한다 피고인 3 , 4 는 피고인 1 에게 고용된 직원으로서 피고인 1 , 2 의 지시에 따라 이 사건 범행을 범하였고,\n분배받은 돈은 그리 많지 않은 점, 피고인들에게 동종전과가 없고, 피고인들이 자신의 잘못을 깊이 뉘우치고\n있는 점, 기타 피고인들의 연령, 성행, 환경 등 이 사건에 나타난 제반 양형조건들을 참작하되, 피고인 3 에 대하여는 작량감경을 하여 각 그 형기 범위 내에서 주문과 같이 형을 정한다. ［별 지］ 범죄일람표 생략\n판사 김득환(재판장) 신숙희 이상덕\n\n【판결 요지】\n［1］ 한국마사회법 제48조 제2항 에서 금지하고 있는 유사행위는 경마참가자들이 ‘마사회가 아닌 자가 소위\n사설경마를 한다는 사정’을 알면서도 그 자에게 ‘마사회에 대하여 하는 승마투표와 유사하게’ 투표를 할 것을\n요건으로 한다. ［2］ 피고인들이 경마경주권의 구매를 대행해주겠다고 피해자들을 기망하였고 이에 속은 피해자들은 자신들\n이 ‘마사회에 대하여 승마투표를 한다고 생각하면서’ 투표를 한 경우, 피해자들이 ‘마사회가 아닌 자에게 승마\n투표와 유사한 행위’를 한 것으로 볼 수 없어 피고인들의 행위는 한국마사회법 제48조 제2항 이 금지하고 있 는 유사행위에 해당하지 않는다고 한 사례. ［3］ 경륜·경정법 제21조 (유사행위의 금지)가 “경주사업자가 아닌 자는 승자투표권 또는 이와 유사한 것을\n발매하거나 승자투표적중자에 대하여 금전을 교부하는 경주 및 승자투표권의 구매·알선·양도 등과 관련한 일 체의 영리행위를 하여서는 아니 된다.”고 규정하고 있어, ‘승자투표권 등 발매행위’, ‘승자투표자에 대한 금전\n교부 행위’, ‘승자투표권의 구매·알선·양도 등’ 중 어느 하나만 위반하여도 위 규정을 위반한 것이 된다.",
  "metadata": {
    "court": "대법원",
    "year": 2006,
    "case_number": "2005고합1157",
    "keywords": [
      "사기",
      "초범",
      "집행유예",
      "벌금",
      "양형"
    ],
    "holding": "［1］ 한국마사회법 제48조 제2항 에서 금지하고 있는 유사행위는 경마참가자들이 ‘마사회가 아닌 자가 소위\n사설경마를 한다는 사정’을 알면서도 그 자에게 ‘마사회에 대하여 하는 승마투표와 유사하게’ 투표를 할 것을\n요건으로 한다. ［2］ 피고인들이 경마경주권의 구매를 대행해주겠다고 피해자들을 기망하였고 이에 속은 피해자들은 자신들\n이 ‘마사회에 대하여 승마투표를 한다고 생각하면서’ 투표를 한 경우, 피해자들이 ‘마사회가 아닌 자에게 승마\n투표와 유사한 행위’를 한 것으로 볼 수 없어 피고인들의 행위는 한국마사회법 제48조 제2항 이 금지하고 있 는 유사행위에 해당하지 않는다고 한 사례. ［3］ 경륜·경정법 제21조 (유사행위의 금지)가 “경주사업자가 아닌 자는 승자투표권 또는 이와 유사한 것을\n발매하거나 승자투표적중자에 대하여 금전을 교부하는 경주 및 승자투표권의 구매·알선·양도 등과 관련한 일 체의 영리행위를 하여서는 아니 된다.”고 규정하고 있어, ‘승자투표권 등 발매행위’, ‘승자투표자에 대한 금전\n교부 행위’, ‘승자투표권의 구매·알선·양도 등’ 중 어느 하나만 위반하여도 위 규정을 위반한 것이 된다.",
    "updated_at": "2025-12-09",
    "judgment_date": "2006-04-21",
    "panji_items": [
      "［1］ 한국마사회법 제48조 제2항 에서 금지하고 있는 유사행위에 해당하기 위한 요건 \n［2］ 피고인들이 경마경주권의 구매를 대행해주겠다고 피해자들을 기망하였고 이에 속은 피해자들은 자신들\n이 ‘마사회에 대하여 승마투표를 한다고 생각하면서’ 투표를 한 경우, 피해자들이 ‘마사회가 아닌 자에게 승마\n투표와 유사한 행위’를 한 것으로 볼 수 없어 피고인들의 행위는 한국마사회법 제48조 제2항 이 금지하고 있\n는 유사행위에 해당하지 않는다고 한 사례 \n［3］ 경륜·경정법 제21조 위반이 되는 행위"
    ],
    "reference_articles": [
      "제48조",
      "제21조"
    ],
    "reference_cases": [
      "대법원 2005. 4. 15. 선고 2004도8971 판결",
      "대법원 2005. 4. 15. 선고 2004도8971"
    ]
  }
}