{
  "id": "case-2005고합201",
  "category": "형사",
  "sub_category": "사기",
  "type": "case",
  "title": "서울동부지방법원 2005고합201 판결",
  "content": "【사건 개요】\n피고인: 피고인 1\n외 3인\n\n【판단】\n가 그러므로 살피건대, 위 각 증거에 의하여 인정되는 다음과 같은 사정들, 즉 피해자들은 재건축에 관한 경 력이 있고, 그렇지 않다고 하더라도 가락시영아파트의 재건축은 대규모의 공사로써 이의 진행경과에 관한 내 용은 약간의 주의만 기울여도 알 수가 있었고, 나아가 피고인 1 이 재건축조합 조합장이 아니라 재건축추진위 원회의 위원장에 불과함을 알면서도, 여러 개의 재건축추진위원회의 상황과 피고인 1 과 공소외 8 이 설립한 재건축조합과의 재건축결의무효확인소송의 추이 등을 지켜보면서 그 승소가능성을 염두에 두고 피고인들로부 터. 향후 재건축조합 설립시 재건축공사관련 이권을 제공하겠다는 약속을 받고 금원을 대여한 것으로 보이는 서울동부지방법원 2005. 11. 4. 선고 2005고합201 판결. 5점, 피해자들은 피고인 1 이 조합인가를 받는 데 실패할 경우에는 원금을 돌려받기로 하였으나 달리 담보를 제공받는 등 원금확보책을 마련하지도 않았다가, 공소외 8 이 조합장이 된 것을 알거나 피고인 1 이 공소외. 16 과의 철거계약과 관련하여 구속된 이후, 또는 피고인 1 이 공소외 8 의 재건축조합과의 항소심에서 패소 한. 이후에야 비로소 대여금의 반환을 요구하였던 점, 일부의 피해자들은 피고인들로부터 기망당한 것이 없다 고. 진술하고 있는 점 등에 비추어 보면 피고인 1 이 조합장의 지위에 있었는지 여부, 피고인 1 이 추진하는 재건축추진위원회의 조합설립가능성에 대한 객관적 사실에 관하여는 피고인들이 적극적으로 피해자들을 기망 하였다고 단정하기 어렵고, 피고인 1 의 재력 여부가 피해자들이 금원을 교부하게 된 계기가 되었다고 보기도 어려우며, 또한 재건축공사관련 이권을 제공하겠다는 약속은 피해자들도 피고인 1 이 재건축조합의 조합장이 아니라는 사실을 알고 있었던 것으로 보이는 점에 비추어 피고인들이 추진하던 재건축조합이 설립인가를 받는 것을 정지조건으로 한 피고인 1 의 의사 자체를 표현의 객체로 삼은 것으로 보이기는 한다 나 그러나 앞서 든 각 증거들에 의하면, ① 피고인 1 은 각 피해자에게 다른 피해자에게는 재건축설계권 또 는 재건축시행권(철거권 포함)을 주었다는 말을 하지 않은 채 재건축설계권 또는 재건축시행권(철거권 포함). 전체를 준다는 동일한 조건으로 각 피해자로부터 금원을 차용한 점, ② 피고인 1 은 그 이전인 2002. 11. 15. 공소외 15 와 사이에 전체 철거공사 중 제1·2공구에 대한 철거공사를 주는 계약을, 2003. 2. 25. 공소외. 16 과 사이에 철거공사 전체를 주는 계약을 이미 각 체결하였던 점, ③ 피해자들은 각 자신에게 위와 같은 재 건축공사관련 이권 전체를 준다는 내용의 재건축설계가계약을 체결하였기 때문에 다른 사람에게 위와 같은 재 건축공사관련 이권을 주었다는 것을 알았다면 피고인 1 과 위의 이권에 관한 계약을 체결하지 않았을 것이라 고. 진술하고 있는 점, ④ 피고인들은 2002. 4. 17.경과 2003. 1. 25. 2회에 걸쳐 피고인 1 을 위원장으로 하 는 재건축추진위원회의 주도로 재건축조합 창립총회를 개최하였으나 아파트 소유자들의 참석률이 저조하여 실 패하였던 점, ⑤ 피고인 1 은 위 위원회의 운영자금으로 차용하였던 금원을 변제하기 위하여 다른 피해자들로 부터 재건축관련이권을 주는 대가로 금원을 계속 차용하였던 점, ⑥ 피고인 1 은 피해자들로부터 차용한 금원 으로 처인 공소외 26 또는 처제인 공소외 27 명의로 부동산 및 외제차 등을 매입한 것으로 보이는 점, ⑦ 피 고인 4 , 2 , 3 은 자신들이 관여하여 금전적인 지원을 받게 된 피해자들을 포함하여 피고인 1 이 동일한 이 권을 조건으로 중북하여 금전적인 지원을 받는다는 것을 알았거나 충분히 알 수 있었다고 보임에도 해당 피해 자들에게 그런한 사실을 고지하지 아니한 점, ⑧ 피고인 1 , 2 , 3 은 피해자 공소외 2 에게는 이미 그 이전 에. 여러 번에 걸쳐 다른 피해자들에게 약속한 재건축시행권을 주거나 금원을 반환하지도 못한 상태에서 피고 인 1 이 공소외 16 과의 철거계약으로 인해 구속되었었다는 사실을 말하지 않은 채 이 사건 계약을 체결하였 던. 것으로 보이는 점 등에 비추어 보면, 피고인 1 은 피해자들로부터 차용한 돈을 피해자들에게 표현한 의사 와는 달리 재건축추진위원회의 운영자금으로만 사용한 것이 아니라 개인적으로도 사용한 것으로 보일 뿐만 아 니라, 피고인들은 위 피해자들에게 표현한 의사에 반하여 다른 피해자들에게 동일한 이권을 제공하기로 약정 한. 것으로서, 피고인들의 위와 같은 각 재건축공사관련 이권제공 약속 또는 이를 대가로 한 재건축추진위원회 운영자금 명목의 금원 차용행위는 기망행위라고 할 것이므로, 피고인들의 위 주장은 이유 없고, 피고인들은 유죄로 인정된다. 1. 범죄사실에 대한 해당법조 및 형의 선택. ○ 피고인 1. 각 형법 제347조 제1항 {각 사기의 점, 판시 제1·2항에 대하여는 각 형법 제30조 , 판시 제1항, 제4의 가 (2). 항의 각 사기의 점은 각 포괄하여, 각 징역형 선택}, 각 특정경제범죄 가중처벌 등에 관한 법률 제3조 제1항 제2호 , 형법 제347조 제1항 , 제30조 {각 특정경제범죄 가중처벌 등에 관한 법률 위반(사기)의 점, 판시 제3. 의 가 항 특정경제범죄 가중처벌 등에 관한 법률 위반(사기)의 점은 포괄하여}, 각 형법 제232조 , 제30조. (각 자격모용사문서작성의 점, 각 징역형 선택), 형법 제307조 제2항 (명예훼손의 점, 징역형 선택). ○ 피고인 4. 형법 제347조 제1항 , 제30조 (사기의 점, 포괄하여, 징역형 선택). ○ 피고인 2. 각 특정경제범죄 가중처벌 등에 관한 법률 제3조 제1항 제2호 , 형법 제347조 제1항 , 제30조 {각 특정경제 범죄 가중처벌 등에 관한 법률 위반(사기)의 점, 판시 제3의 가 항 특정경제범죄 가중처벌 등에 관한 법률 위 서울동부지방법원 2005. 11. 4. 선고 2005고합201 판결. 6반(사기)의 점은 포괄하여}, 각 형법 제232조 , 제30조 (각 자격모용사문서작성의 점, 각 징역형 선택). ○ 피고인 3. 각 특정경제범죄 가중처벌 등에 관한 법률 제3조 제1항 제2호 , 형법 제347조 제1항 , 제30조 {각 특정경제 범죄 가중처벌 등에 관한 법률 위반(사기)의 점, 판시 제3의 가 항 특정경제범죄 가중처벌 등에 관한 법률 위 반(사기)의 점은 포괄하여}, 각 형법 제232조 , 제30조 (각 자격모용사문서작성의 점, 각 징역형 선택), 변호 사법 제111조 (청탁 명목 금품수수의 점, 징역형 선택). 1. 누범 가중. ○ 피고인 1 : 판시 제1항 및 제4의 가 (1)·(2)항의 각 사기죄에 대하여 각 형법 제35조. ○ 피고인 3 : 각 형법 제35조 {다만, 특정경제범죄 가중처벌 등에 관한 법률 위반(사기)죄에 대하여는 형법 제42조 단서의 제한 내에서}. 1. 경합범 가중. ○ 피고인 1 , 2 , 3 : 각 형법 제37조 전단, 제38조 제1항 제2호 , 제50조 {각 형과 범정이 가장 무거운 판 시 제3의 다 항 특정경제범죄 가중처벌 등에 관한 법률 위반(사기)죄에 정한 형에 각 경합범 가중, 다만 피고 인 3 에 대하여는 형법 제42조 단서의 제한 내에서}. 1. 작량감경. ○ 피고인 1 , 2 , 3 : 형법 제53조 , 제55조 제1항 제3호 (아래 양형의 이유 중 위 피고인들에게 유리한 정 상을 각 참작). 1. 미결구금일수 산입. ○ 피고인들 : 각 형법 제57조. 1. 집행유예. ○ 피고인 4 , 2 : 각 2005. 7. 29. 개정 후의 형법 제62조 제1항 (아래 양형의 이유 중 위 피고인들에게 유 리한 정상을 각 참작). 1. 추징. ○ 피고인 3 : 변호사법 제116조. 1. 공소사실의 요지 피고인 1 , 4 는 재건축과 관련된 철거업자·시공사·설계자의 선정 업무는 도시 및 주거환경정비법상 총회의 의결사항으로 규정되어 있고, 업체선정을 위해서는 경쟁입찰 등의 방법으로 해당업체의 시행능력과 공사금액 등을 공정하게 평가하여야 하며, 조합원 총회의 의결을 거치는 등의 절차를 밟아야 할 뿐 아니라, 재건축을 추진 중인 가락시영아파트 단지에는 1997년부터 5개의 재건축 추진위원회가 이미 설립되어 피고인들과 상호 경쟁을 하다가 공소외 8 이 2003. 5. 24. 조합 창립총회에서 조합장으로 선출되었고, 2003. 6\n\n【판결 요지】\n피고인 1 , 4 는 재건축과 관련된 철거업자·시공사·설계자의 선정 업무는 도시 및 주거환경정비법상 총회의\n의결사항으로 규정되어 있고, 업체선정을 위해서는 경쟁입찰 등의 방법으로 해당업체의 시행능력과 공사금액\n등을 공정하게 평가하여야 하며, 조합원 총회의 의결을 거치는 등의 절차를 밟아야 할 뿐 아니라, 재건축을\n추진 중인 가락시영아파트 단지에는 1997년부터 5개의 재건축 추진위원회가 이미 설립되어 피고인들과 상호\n경쟁을 하다가 공소외 8 이 2003. 5. 24. 조합 창립총회에서 조합장으로 선출되었고, 2003. 6. 12. 송파구청\n으로부터 재건축조합 설립인가를 받았으며, 조합설립 이전 단계의 재건축추진위원회는 재건축 시행과 관련된\n업체선정 등의 계약을 체결할 권한이 없음에도 불구하고, 2002. 9. 18.경 서울 송파구 석촌동 273-3 소재 임 지빌딩 301호 가락시영아파트 재건축추진위원회 사무실에서 공소외 32 법무사사무실 직원 피해자 공소외 7\n에게 ‘재건축조합 총회를 개최 하려는데 비용이 필요하니 돈을 차용해주면 조합 설립 후 입주자들에 대한 등 기업무를 할 수 있도록 해주겠다’고 말하여 피해자를 기망하고, 이에 속은 피해자로부터 즉석에서 금 5,000만\n원을 교부받고, 같은 해 12. 10.경 금 5,000만 원을 교부받아 합계 1억 원을 편취하였다. 2. 피고인 1 , 4 의 변소 요지\n위 피고인들은 피해자가 먼저 접근해 와 운영자금을 대여해주겠다고 제의하여 차용증을 써주고 차용한 것일\n뿐, 조합설립 후 입주자들에 대한 등기업무를 할 수 있도록 해주겠다는 약속을 한 바 없다거나, 또는 피해자\n가 피고인이 추진하고 있던 재건축조합이 설립될 경우 재건축관련 등기업무를 수주하는 과정에서 편의를 제공\n받기 위하여 자발적으로 대여한 것으로서 편취한 것이 아니라고 주장하고 있다. 3. 판 단\n가 피고인 1 , 4 의 이 법정 및 수사기관에서의 각 일부 진술, 공소외 32 와 공소외 7 의 이 법정 및 수사기\n관에서의 진술, 각 차용증 및 각 수표 사.",
  "metadata": {
    "court": "서울동부지방법원",
    "year": 2005,
    "case_number": "2005고합201",
    "keywords": [
      "사기",
      "협박",
      "초범",
      "집행유예",
      "실형"
    ],
    "holding": "피고인 1 , 4 는 재건축과 관련된 철거업자·시공사·설계자의 선정 업무는 도시 및 주거환경정비법상 총회의\n의결사항으로 규정되어 있고, 업체선정을 위해서는 경쟁입찰 등의 방법으로 해당업체의 시행능력과 공사금액\n등을 공정하게 평가하여야 하며, 조합원 총회의 의결을 거치는 등의 절차를 밟아야 할 뿐 아니라, 재건축을\n추진 중인 가락시영아파트 단지에는 1997년부터 5개의 재건축 추진위원회가 이미 설립되어 피고인들과 상호\n경쟁을 하다가 공소외 8 이 2003. 5. 24. 조합 창립총회에서 조합장으로 선출되었고, 2003. 6. 12. 송파구청\n으로부터 재건축조합 설립인가를 받았으며, 조합설립 이전 단계의 재건축추진위원회는 재건축 시행과 관련된\n업체선정 등의 계약을 체결할 권한이 없음에도 불구하고, 2002. 9. 18.경 서울 송파구 석촌동 273-3 소재 임 지빌딩 301호 가락시영아파트 재건축추진위원회 사무실에서 공소외 32 법무사사무실 직원 피해자 공소외 7\n에게 ‘재건축조합 총회를 개최 하려는데 비용이 필요하니 돈을 차용해주면 조합 설립 후 입주자들에 대한 등 기업무를 할 수 있도록 해주겠다’고 말하여 피해자를 기망하고, 이에 속은 피해자로부터 즉석에서 금 5,000만\n원을 교부받고, 같은 해 12. 10.경 금 5,000만 원을 교부받아 합계 1억 원을 편취하였다. 2. 피고인 1 , 4 의 변소 요지\n위 피고인들은 피해자가 먼저 접근해 와 운영자금을 대여해주겠다고 제의하여 차용증을 써주고 차용한 것일\n뿐, 조합설립 후 입주자들에 대한 등기업무를 할 수 있도록 해주겠다는 약속을 한 바 없다거나, 또는 피해자\n가 피고인이 추진하고 있던 재건축조합이 설립될 경우 재건축관련 등기업무를 수주하는 과정에서 편의를 제공\n받기 위하여 자발적으로 대여한 것으로서 편취한 것이 아니라고 주장하고 있다. 3. 판 단\n가 피고인 1 , 4 의 이 법정 및 수사기관에서의 각 일부 진술, 공소외 32 와 공소외 7 의 이 법정 및 수사기\n관에서의 진술, 각 차용증 및 각 수표 사...",
    "updated_at": "2025-12-09",
    "judgment_date": "2005-11-04",
    "reference_articles": [
      "형법 제347조",
      "형법 제30조",
      "형법 제232조",
      "형법 제307조",
      "형법 제35조",
      "형법 \n제42조",
      "형법 제37조",
      "형법 제42조",
      "형법 제53조",
      "형법 제57조",
      "형법 제62조",
      "특정경제범죄 가중처벌 등에 관한 법률 제3조",
      "형사소송법 제325조"
    ]
  }
}